score.shell-0.1.2-py3.4-nspkg.pth
score/shell/__init__.py
score/shell/_init.py
score/shell/cli.py
score.shell-0.1.2.dist-info/DESCRIPTION.rst
score.shell-0.1.2.dist-info/METADATA
score.shell-0.1.2.dist-info/RECORD
score.shell-0.1.2.dist-info/WHEEL
score.shell-0.1.2.dist-info/entry_points.txt
score.shell-0.1.2.dist-info/metadata.json
score.shell-0.1.2.dist-info/namespace_packages.txt
score.shell-0.1.2.dist-info/top_level.txt
